[{"location_name":"West Sussex","age_group_name":"All Ages","year_id":1950,"male":276134.2017,"female":330275.2996,"both":606409.5012},{"location_name":"West Sussex","age_group_name":"All Ages","year_id":1951,"male":275573.3379,"female":328907.3463,"both":604480.6842},{"location_name":"West Sussex","age_group_name":"All Ages","year_id":1952,"male":274910.8002,"female":327490.5971,"both":602401.3973},{"location_name":"West Sussex","age_group_name":"All Ages","year_id":1953,"male":274273.3546,"female":326129.966,"both":600403.3205},{"location_name":"West Sussex","age_group_name":"All Ages","year_id":1954,"male":273648.3232,"female":324810.7543,"both":598459.0774},{"location_name":"West Sussex","age_group_name":"All Ages","year_id":1955,"male":272995.851,"female":323514.3237,"both":596510.1747},{"location_name":"West Sussex","age_group_name":"All Ages","year_id":1956,"male":272353.4917,"female":322276.3123,"both":594629.804},{"location_name":"West Sussex","age_group_name":"All Ages","year_id":1957,"male":271788.5679,"female":321161.0904,"both":592949.6583},{"location_name":"West Sussex","age_group_name":"All Ages","year_id":1958,"male":271330.2395,"female":320175.7258,"both":591505.9653},{"location_name":"West Sussex","age_group_name":"All Ages","year_id":1959,"male":271034.106,"female":319358.5809,"both":590392.6869},{"location_name":"West Sussex","age_group_name":"All Ages","year_id":1960,"male":270910.7208,"female":318719.1449,"both":589629.8657},{"location_name":"West Sussex","age_group_name":"All Ages","year_id":1961,"male":270937.542,"female":318233.8646,"both":589171.4066},{"location_name":"West Sussex","age_group_name":"All Ages","year_id":1962,"male":271117.0787,"female":317919.147,"both":589036.2256},{"location_name":"West Sussex","age_group_name":"All Ages","year_id":1963,"male":271492.1708,"female":317845.3495,"both":589337.5202},{"location_name":"West Sussex","age_group_name":"All Ages","year_id":1964,"male":272123.1517,"female":318073.1613,"both":590196.313},{"location_name":"West Sussex","age_group_name":"All Ages","year_id":1965,"male":273057.9626,"female":318628.2563,"both":591686.2189},{"location_name":"West Sussex","age_group_name":"All Ages","year_id":1966,"male":274217.1481,"female":319398.6696,"both":593615.8177},{"location_name":"West Sussex","age_group_name":"All Ages","year_id":1967,"male":275673.3242,"female":320455.5691,"both":596128.8933},{"location_name":"West Sussex","age_group_name":"All Ages","year_id":1968,"male":277410.6627,"female":321787.0279,"both":599197.6906},{"location_name":"West Sussex","age_group_name":"All Ages","year_id":1969,"male":279433.9157,"female":323427.9468,"both":602861.8624},{"location_name":"West Sussex","age_group_name":"All Ages","year_id":1970,"male":281818.7091,"female":325454.497,"both":607273.2061},{"location_name":"West Sussex","age_group_name":"All Ages","year_id":1971,"male":284659.2141,"female":327940.8163,"both":612600.0304},{"location_name":"West Sussex","age_group_name":"All Ages","year_id":1972,"male":287931.7536,"female":330844.9208,"both":618776.6744},{"location_name":"West Sussex","age_group_name":"All Ages","year_id":1973,"male":291496.7844,"female":334032.8015,"both":625529.5858},{"location_name":"West Sussex","age_group_name":"All Ages","year_id":1974,"male":295263.6807,"female":337411.2596,"both":632674.9404},{"location_name":"West Sussex","age_group_name":"All Ages","year_id":1975,"male":299130.7941,"female":340873.2159,"both":640004.01},{"location_name":"West Sussex","age_group_name":"All Ages","year_id":1976,"male":303025.7387,"female":344348.8976,"both":647374.6362},{"location_name":"West Sussex","age_group_name":"All Ages","year_id":1977,"male":306878.8311,"female":347791.9177,"both":654670.7488},{"location_name":"West Sussex","age_group_name":"All Ages","year_id":1978,"male":310737.967,"female":351282.5868,"both":662020.5538},{"location_name":"West Sussex","age_group_name":"All Ages","year_id":1979,"male":314479.2749,"female":354690.7889,"both":669170.0638},{"location_name":"West Sussex","age_group_name":"All Ages","year_id":1980,"male":318007.7748,"female":357925.5126,"both":675933.2874},{"location_name":"West Sussex","age_group_name":"All Ages","year_id":1981,"male":321112.2499,"female":360768.2991,"both":681880.549},{"location_name":"West Sussex","age_group_name":"All Ages","year_id":1982,"male":323637.2739,"female":363028.1439,"both":686665.4178},{"location_name":"West Sussex","age_group_name":"All Ages","year_id":1983,"male":325731.7674,"female":364816.4754,"both":690548.2427},{"location_name":"West Sussex","age_group_name":"All Ages","year_id":1984,"male":327483.0459,"female":366262.5734,"both":693745.6193},{"location_name":"West Sussex","age_group_name":"All Ages","year_id":1985,"male":328931.964,"female":367379.3976,"both":696311.3616},{"location_name":"West Sussex","age_group_name":"All Ages","year_id":1986,"male":330242.9864,"female":368336.0806,"both":698579.067},{"location_name":"West Sussex","age_group_name":"All Ages","year_id":1987,"male":331560.2579,"female":369363.6653,"both":700923.9231},{"location_name":"West Sussex","age_group_name":"All Ages","year_id":1988,"male":332932.0126,"female":370443.2454,"both":703375.2581},{"location_name":"West Sussex","age_group_name":"All Ages","year_id":1989,"male":334415.5779,"female":371598.3824,"both":706013.9604},{"location_name":"West Sussex","age_group_name":"All Ages","year_id":1990,"male":336052.097,"female":372981.7007,"both":709033.7977},{"location_name":"West Sussex","age_group_name":"All Ages","year_id":1991,"male":337866.1773,"female":374660.6638,"both":712526.8411},{"location_name":"West Sussex","age_group_name":"All Ages","year_id":1992,"male":339879.6822,"female":376584.635,"both":716464.3172},{"location_name":"West Sussex","age_group_name":"All Ages","year_id":1993,"male":342111.0522,"female":378662.8916,"both":720773.9438},{"location_name":"West Sussex","age_group_name":"All Ages","year_id":1994,"male":344580.52,"female":380856.2673,"both":725436.7873},{"location_name":"West Sussex","age_group_name":"All Ages","year_id":1995,"male":347264.7576,"female":383200.9365,"both":730465.6941},{"location_name":"West Sussex","age_group_name":"All Ages","year_id":1996,"male":350117.7528,"female":385694.08,"both":735811.8328},{"location_name":"West Sussex","age_group_name":"All Ages","year_id":1997,"male":353170.7528,"female":388317.1304,"both":741487.8833},{"location_name":"West Sussex","age_group_name":"All Ages","year_id":1998,"male":356321.6511,"female":390994.6615,"both":747316.3126},{"location_name":"West Sussex","age_group_name":"All Ages","year_id":1999,"male":359356.1563,"female":393530.9278,"both":752887.0841},{"location_name":"West Sussex","age_group_name":"All Ages","year_id":2000,"male":362285.4948,"female":395863.2407,"both":758148.7354},{"location_name":"West Sussex","age_group_name":"All Ages","year_id":2001,"male":365168.5651,"female":398035.6648,"both":763204.2299},{"location_name":"West Sussex","age_group_name":"All Ages","year_id":2002,"male":368052.4502,"female":400090.7143,"both":768143.1645},{"location_name":"West Sussex","age_group_name":"All Ages","year_id":2003,"male":370978.9691,"female":402171.0277,"both":773149.9968},{"location_name":"West Sussex","age_group_name":"All Ages","year_id":2004,"male":374021.1085,"female":404464.5056,"both":778485.6141},{"location_name":"West Sussex","age_group_name":"All Ages","year_id":2005,"male":377150.1899,"female":406861.943,"both":784012.133},{"location_name":"West Sussex","age_group_name":"All Ages","year_id":2006,"male":380396.6089,"female":409362.1779,"both":789758.7868},{"location_name":"West Sussex","age_group_name":"All Ages","year_id":2007,"male":383700.2538,"female":411888.8158,"both":795589.0696},{"location_name":"West Sussex","age_group_name":"All Ages","year_id":2008,"male":386986.5328,"female":414366.1225,"both":801352.6553},{"location_name":"West Sussex","age_group_name":"All Ages","year_id":2009,"male":390220.3463,"female":416837.7903,"both":807058.1366},{"location_name":"West Sussex","age_group_name":"All Ages","year_id":2010,"male":393431.2967,"female":419264.8536,"both":812696.1503},{"location_name":"West Sussex","age_group_name":"All Ages","year_id":2011,"male":396555.9881,"female":421568.4549,"both":818124.4429},{"location_name":"West Sussex","age_group_name":"All Ages","year_id":2012,"male":399486.4455,"female":423703.3798,"both":823189.8253},{"location_name":"West Sussex","age_group_name":"All Ages","year_id":2013,"male":402151.2307,"female":425643.916,"both":827795.1467},{"location_name":"West Sussex","age_group_name":"All Ages","year_id":2014,"male":404668.9457,"female":427556.0407,"both":832224.9864},{"location_name":"West Sussex","age_group_name":"All Ages","year_id":2015,"male":407116.5878,"female":429469.9483,"both":836586.5361},{"location_name":"West Sussex","age_group_name":"All Ages","year_id":2016,"male":409497.9491,"female":431389.6933,"both":840887.6423},{"location_name":"West Sussex","age_group_name":"All Ages","year_id":2017,"male":411833.2163,"female":433274.1302,"both":845107.3465},{"location_name":"West Sussex","age_group_name":"All Ages","year_id":2018,"male":413997.8636,"female":435001.1364,"both":848999},{"location_name":"West Sussex","age_group_name":"All Ages","year_id":2019,"male":416025.1294,"female":436640.9406,"both":852666.07}]
